amaz3dpy/__init__.py
amaz3dpy/auth.py
amaz3dpy/clients/__init__.py
amaz3dpy/clients/cli.py
amaz3dpy/clients/client.py
amaz3dpy/customer_wallet.py
amaz3dpy/items.py
amaz3dpy/models.py
amaz3dpy/optimization_templates.py
amaz3dpy/optimizations.py
amaz3dpy/projects.py
amaz3dpy/terms.py
amaz3dpy/webapiclients/__init__.py
amaz3dpy/webapiclients/gqlhttpclient.py
amaz3dpy/webapiclients/gqlwebsocketsclient.py
amaz3dpy-0.1.7.dist-info/entry_points.txt
amaz3dpy-0.1.7.dist-info/WHEEL
amaz3dpy-0.1.7.dist-info/METADATA
amaz3dpy-0.1.7.dist-info/RECORD
